emo/__init__.py
emo/code.py
emo-0.3.2.dist-info/DESCRIPTION.rst
emo-0.3.2.dist-info/METADATA
emo-0.3.2.dist-info/RECORD
emo-0.3.2.dist-info/WHEEL
emo-0.3.2.dist-info/entry_points.txt
emo-0.3.2.dist-info/metadata.json
emo-0.3.2.dist-info/top_level.txt
